odoo/addons/stock_move_not_merge_by_dest_moves/README.rst
odoo/addons/stock_move_not_merge_by_dest_moves/__init__.py
odoo/addons/stock_move_not_merge_by_dest_moves/__manifest__.py
odoo/addons/stock_move_not_merge_by_dest_moves/i18n/stock_move_not_merge_by_dest_moves.pot
odoo/addons/stock_move_not_merge_by_dest_moves/models/__init__.py
odoo/addons/stock_move_not_merge_by_dest_moves/models/stock_move.py
odoo/addons/stock_move_not_merge_by_dest_moves/readme/CONTEXT.md
odoo/addons/stock_move_not_merge_by_dest_moves/readme/CONTRIBUTORS.md
odoo/addons/stock_move_not_merge_by_dest_moves/readme/CREDITS.md
odoo/addons/stock_move_not_merge_by_dest_moves/readme/DESCRIPTION.md
odoo/addons/stock_move_not_merge_by_dest_moves/readme/ROADMAP.md
odoo/addons/stock_move_not_merge_by_dest_moves/readme/USAGE.md
odoo/addons/stock_move_not_merge_by_dest_moves/static/description/icon.png
odoo/addons/stock_move_not_merge_by_dest_moves/static/description/index.html
odoo/addons/stock_move_not_merge_by_dest_moves/tests/__init__.py
odoo/addons/stock_move_not_merge_by_dest_moves/tests/test_stock_move.py
odoo_addon_stock_move_not_merge_by_dest_moves-16.0.1.0.1.dist-info/METADATA
odoo_addon_stock_move_not_merge_by_dest_moves-16.0.1.0.1.dist-info/WHEEL
odoo_addon_stock_move_not_merge_by_dest_moves-16.0.1.0.1.dist-info/top_level.txt
odoo_addon_stock_move_not_merge_by_dest_moves-16.0.1.0.1.dist-info/RECORD
